clearskies_akeyless_custom_gitlab/__init__.py
clearskies_akeyless_custom_gitlab/common.py
clearskies_akeyless_custom_gitlab/create.py
clearskies_akeyless_custom_gitlab/errors.py
clearskies_akeyless_custom_gitlab/revoke.py
clearskies_akeyless_custom_gitlab/rotate.py
clear_skies_akeyless_custom_gitlab-2.0.2.dist-info/METADATA
clear_skies_akeyless_custom_gitlab-2.0.2.dist-info/WHEEL
clear_skies_akeyless_custom_gitlab-2.0.2.dist-info/licenses/LICENSE
clear_skies_akeyless_custom_gitlab-2.0.2.dist-info/RECORD
