Metadata-Version: 2.4
Name: clear-skies-akeyless-custom-gitlab
Version: 2.0.2
Summary: Akeyless+Clearskies Custom Gitlab Producer/Rotator
Project-URL: Repository, https://github.com/clearskies-akeyless-custom-producers/gitlab
Project-URL: Issues, https://github.com/clearskies-akeyless-custom-producers/gitlab/issues
Project-URL: Changelog, https://github.com/clearskies-akeyless-custom-producers/gitlab/blob/main/CHANGELOG.md
Author-email: Tom Nijboer <tom.nijboer@cimpress.com>
License-Expression: MIT
License-File: LICENSE
Classifier: Development Status :: 5 - Production/Stable
Classifier: Intended Audience :: Developers
Classifier: License :: OSI Approved :: MIT License
Classifier: Programming Language :: Python :: 3
Requires-Python: <4.0,>=3.11
Requires-Dist: clear-skies-akeyless-custom-producer<3.0.0,>=2.0.0
Requires-Dist: clear-skies<3.0.0,>=2.0.0
Requires-Dist: requests<3.0.0,>=2.0.0
Provides-Extra: dev
Requires-Dist: types-requests>=2.32.4; extra == 'dev'
